Workbook

Sheet Cuadre Diario
A1: FECHA | B1: CAJA INICIO | C1: VENTAS DEL DIA | D1: VENTA CON TARJETAS | E1: NOMINA | F1: DESCUENTOS | G1: COMPRAS | H1: SERVICIOS | I1: OTROS PAGOS | J1: VALOR EN CAJA
A4: 45870 | B4: 300000 | C4: 1840320 | D4: 432500 | E4: =+Nomina!E12 -> 307831 | G4: =+Compras!H22 -> 1114257 | J4: =+C4-D4-E4-F4-G4-H4-I4 -> -14268
A5: 45871 | B5: 300000 | C5: 2778300 | D5: 532620 | E5: =+Nomina!E22 -> 283282 | G5: =+Compras!H36 -> 526510 | J5: =+C5-D5-E5-F5-G5-H5-I5 -> 1435888
A6: 45872 | B6: 300000 | C6: 2333880 | D6: 496000 | E6: =+Nomina!E31 -> 242798 | G6: =+Compras!H50 -> 371036 | J6: =+C6-D6-E6-F6-G6-H6-I6 -> 1224046
A7: 45873 | B7: 300000 | C7: 1245810 | D7: 206900 | E7: =+Nomina!E40 -> 149448 | G7: =+Compras!H64 -> 789334 | J7: =+C7-D7-E7-F7-G7-H7-I7 -> 100128
A8: 45874 | B8: 300000 | C8: 998650 | D8: 102200 | E8: =+Nomina!E47 -> 193483 | G8: =+Compras!H75 -> 548500 | J8: =+C8-D8-E8-F8-G8-H8-I8 -> 154467
A9: 45875 | B9: 300000 | C9: 1303870 | D9: 272130 | E9: =+Nomina!E55 -> 189985 | G9: =+Compras!H90 -> 661707 | J9: =+C9-D9-E9-F9-G9-H9-I9 -> 180048
A10: 45876 | B10: 300000 | C10: 2284050 | D10: 432580 | E10: =+Nomina!E62 -> 253938 | G10: =+Compras!H103 -> 775320 | J10: =+C10-D10-E10-F10-G10-H10-I10 -> 822212
A11: 45877 | B11: 300000 | C11: 1632750 | D11: 351200 | E11: =+Nomina!E69 -> 211087 | G11: =+Compras!H115 -> 819254 | J11: =+C11-D11-E11-F11-G11-H11-I11 -> 251209
A12: 45878 | B12: 300000 | C12: 2255370 | D12: 425100 | E12: =+Nomina!E76 -> 230927 | G12: =+Compras!H130 -> 522354 | J12: =+C12-D12-E12-F12-G12-H12-I12 -> 1076989
A13: 45879 | B13: 300000 | C13: 2449240 | D13: 759200 | E13: =+Nomina!E84 -> 248354 | G13: =+Compras!H143 -> 489000 | I13: =+'Otros Pagos'!G6 -> 150000 | J13: =+C13-D13-E13-F13-G13-H13-I13 -> 802686
A14: 45880 | B14: 300000 | C14: 1188470 | D14: 197500 | E14: =+Nomina!E93 -> 185202 | G14: =+Compras!H153 -> 709778 | J14: =+C14-D14-E14-F14-G14-H14-I14 -> 95990
A15: 45881 | B15: 300000 | C15: 1354590 | D15: 284500 | E15: =+Nomina!E101 -> 265947 | G15: =+Compras!H162 -> 301930 | J15: =+C15-D15-E15-F15-G15-H15-I15 -> 502213
A16: 45882 | B16: 300000 | C16: 1115205 | D16: 362100 | E16: =+Nomina!E109 -> 190554 | G16: =+Compras!H173 -> 658363 | J16: =+C16-D16-E16-F16-G16-H16-I16 -> -95812
A17: 45883 | B17: 300000 | C17: 1081780 | D17: 192100 | E17: =+Nomina!E118 -> 155888 | G17: =+Compras!H182 -> 319000 | J17: =+C17-D17-E17-F17-G17-H17-I17 -> 414792
A18: 45884 | B18: 300000 | C18: 1424160 | D18: 368810 | E18: =+Nomina!E126 -> 204616 | G18: =+Compras!H197 -> 965915 | J18: =+C18-D18-E18-F18-G18-H18-I18 -> -115181
A19: 45885 | B19: 300000 | C19: 2544340 | D19: 487300 | E19: =+Nomina!E132 -> 191472 | G19: =+Compras!H214 -> 1116974 | J19: =+C19-D19-E19-F19-G19-H19-I19 -> 748594
A20: 45886 | B20: 300000 | C20: 2861300 | D20: 807700 | E20: =+Nomina!E141 -> 270648 | G20: =+Compras!H226 -> 227192 | J20: =+C20-D20-E20-F20-G20-H20-I20 -> 1555760
A21: 45887 | B21: 300000 | C21: 2066400 | D21: 503700 | E21: =+Nomina!E150 -> 401486 | G21: =+Compras!H241 -> 664102 | J21: =+C21-D21-E21-F21-G21-H21-I21 -> 497112
A22: 45888 | B22: 300000 | C22: 1148700 | D22: 136400 | E22: =+Nomina!E157 -> 191319 | G22: =+Compras!H252 -> 466552 | H22: =+Servicios!E3 -> 146650 | J22: =+C22-D22-E22-F22-G22-H22-I22 -> 207779 | K22: Pte factura éxito César
A23: 45889 | B23: 500000 | C23: 1200160 | D23: 370400 | E23: =+Nomina!E170 -> 180848 | G23: =+Compras!H263 -> 683939 | I23: =+'Otros Pagos'!G11 -> 307900 | J23: =+C23-D23-E23-F23-G23-H23-I23 -> -342927
A24: 45890 | B24: 500000 | C24: 817190 | D24: 166030 | E24: =+Nomina!E177 -> 116868 | G24: =+Compras!H272 -> 363730 | J24: =+C24-D24-E24-F24-G24-H24-I24 -> 170562 | K24: Desde aquí
A25: 45891 | B25: 500000 | C25: 1767070 | D25: 590060 | E25: =+Nomina!E186 -> 217753 | G25: =+Compras!H291 -> 901742 | J25: =+C25-D25-E25-F25-G25-H25-I25 -> 57515
A26: 45892 | B26: 500000 | C26: 2116520 | D26: 639800 | E26: =+Nomina!E194 -> 188243 | G26: =+Compras!H306 -> 842738 | J26: =+C26-D26-E26-F26-G26-H26-I26 -> 445739
A27: 45893 | B27: 500000 | C27: 1549130 | D27: 389500 | E27: =+Nomina!E201 -> 209378 | G27: =+Compras!H315 -> 444172 | J27: =+C27-D27-E27-F27-G27-H27-I27 -> 506080
A28: 45894 | B28: 500000 | C28: 977090 | D28: 239200 | E28: =+Nomina!E207 -> 152652 | G28: =+Compras!H325 -> 179372 | J28: =+C28-D28-E28-F28-G28-H28-I28 -> 405866
A29: 45895 | B29: 500000 | C29: 920190 | D29: 152400 | E29: =+Nomina!E215 -> 113632 | G29: =+Compras!H337 -> 321228 | J29: =+C29-D29-E29-F29-G29-H29-I29 -> 332930
A30: 45896 | B30: 500000 | C30: 1196120 | D30: 285700 | E30: =+Nomina!E223 -> 246944 | G30: =+Compras!H349 -> 547798 | H30: =+Servicios!E4 -> 135000 | I30: =+'Otros Pagos'!G15 -> 150000 | J30: =+C30-D30-E30-F30-G30-H30-I30 -> -169322
A31: 45897 | B31: 500000 | C31: 1110440 | D31: 251900 | E31: =+Nomina!E230 -> 154769 | G31: =+Compras!H362 -> 394080 | J31: =+C31-D31-E31-F31-G31-H31-I31 -> 309691
A32: 45898 | B32: 500000 | C32: 1617130 | D32: 407800 | E32: =+Nomina!E237 -> 211086 | G32: =+Compras!H377 -> 962120 | J32: =+C32-D32-E32-F32-G32-H32-I32 -> 36124
A33: 45899 | B33: 500000 | C33: 2154510 | D33: 816700 | E33: =+Nomina!E243 -> 162360 | G33: =+Compras!H393 -> 744612 | J33: =+C33-D33-E33-F33-G33-H33-I33 -> 430838
A34: 45900 | B34: 500000 | C34: 1812410 | D34: 222400 | E34: =+Nomina!E252 -> 778368 | G34: =+Compras!H402 -> 362040 | J34: =+C34-D34-E34-F34-G34-H34-I34 -> 449602
C36: =SUM(C4:C35) -> 51145145 | D36: =SUM(D4:D35) -> 11882430 | E36: =SUM(E4:E35) -> 7101166 | F36: =SUM(F4:F35) -> 0 | G36: =SUM(G4:G35) -> 18794649 | H36: =SUM(H4:H35) -> 281650 | I36: =SUM(I4:I35) -> 607900 | J36: =SUM(J4:J35) -> 12477350
G41: UTILID NETA | I41: =+J36+D36-3500000 -> 20859780

Sheet Nomina
A1: FECHA | B1: NOMBRE | C1: CEDULA O NIT | D1: DETALLE | E1: VALOR | F1: Yomara | G1: Maryuri | H1: Olaga | I1: Lina | J1: Natalia | K1: Yessica | L1: Karen | M1: Melissa
A3: 45870 | B3: Yessica Viscaya | D3: 4 a 9 30 | E3: 42256 | K3: 5.5
B4: Karen Vaquero | D4: 3 a 9 30 | E4: 48727 | L4: 6.5
B5: Yomara González | D5: 1 a 8 | E5: 51963 | F5: 7
B6: Natalia Ríos | D6: 10 a 4 30 | E6: 48727 | J6: 6.5
B7: Laura Pulecio | D7: 9 30 a 3 30 | E7: 45492
B8: Olga Pulecio | D8: Pago | E8: 70666
A12: PAGO NÓMINA DEL 01/8/2025 | E12: =SUM(E3:E11) -> 307831
A14: 45871 | B14: Karen Vaquero | D14: 10 a 8 3074611 | E14: 74611 | L14: 10.5
B15: Yomara González | D15: 3 a 9 | E15: 45492 | F15: 6
B16: Natalia Ríos | D16: 2 a 9 | E16: 51963 | J16: 7
B17: Laura Pulecio | D17: 2 a 6 | E17: 32550
B18: Olga Pulecio | D18: 9 30 a 6 30 | E18: 78666
A22: PAGO NÓMINA DEL 02/8/2025 | E22: =SUM(E14:E21) -> 283282
A24: 45872 | B24: Karen Vaquero | D24: 1 a 8 | E24: 84646 | L24: 7
B25: Yomara González | D25: 11 a 6 | E25: 84646 | F25: 7
B26: Natalia Ríos | D26: 2 a 8 | E26: 73506 | J26: 6
A31: PAGO NÓMINA DEL 03/8/2025 | E31: =SUM(E24:E30) -> 242798
A33: 45873 | B33: Yomara González | D33: 11 a 7 30 | E33: 61700 | F33: 8.5
B34: Natalia Ríos | D34: 9 a 4 | E34: 51963 | J34: 7
B35: Yessica | D35: 4 a 8 30 | E35: 35785 | K35: 4.5
A40: PAGO NÓMINA DEL 04/8/2025 | E40: =SUM(E33:E39) -> 149448
A42: 45874 | B42: Yomara González | D42: 3 a 8 30 | E42: 42256 | F42: 5
B43: Natalia Ríos | D43: 10 a 4 | E43: 45168 | J43: 6
B44: Karen Vaquero | D44: 2 a 8 30 | E44: 48727 | L44: 6.5
B45: Olga Pulecio | D45: Pago | E45: 57332
A47: PAGO NÓMINA DEL 05/8/2025 | E47: =SUM(E42:E46) -> 193483
A49: 678/2025 | B49: Yomara González | D49: 2 a 8 | E49: 45492 | F49: 6
B50: Natalia Ríos | D50: 10 a 4 | E50: 45492 | J50: 6
B51: Olga Pulecio | D51: Pago | E51: 30666
B52: Yessica Viscaya | D52: 4 a 8 | E52: 32550 | K52: 4
B53: Laura Pulecio | D53: 2 a 6 30 | E53: 35785
A55: PAGO NÓMINA DEL 06/8/2025 | E55: =SUM(E49:E54) -> 189985
A57: 45876 | B57: Karen Vaquero | D57: 1 a 8 30 | E57: 90216 | L57: 7.5
B58: Yomara González | D58: 11 a 8 | E58: 106926 | F58: 9
B59: Laura Pulecio | D59: 1 a 5 30 | E59: 56796
A62: PAGO NÓMINA DEL 07/8/2025 | E62: =SUM(E57:E61) -> 253938
A64: 45877 | B64: Karen Vaquero | D64: 11 a 7 30 | E64: 61669 | L64: 8.5
B65: Yomara González | D65: 1 a 9 | E65: 58434 | F65: 7
B66: Yessica Viscaya | D66: 4 a 9 | E66: 39021 | K66: 5
B67: Natalia Ríos | D67: 9 a 4 | E67: 51963 | J67: 7
A69: PAGO NÓMINA DEL 08/8/2025 | E69: =SUM(E64:E68) -> 211087
A71: 45878 | B71: Karen Vaquero | D71: 3 a 9 | E71: 45492 | L71: 6
B72: Yomara González | D72: 1 a 9 30 | E72: 61669 | F72: 8.5
B73: Olga Pulecio | D73: Pago | E73: 65332
B74: Natalia Ríos | D74: 8 horas | E74: 58434 | J74: 8
A76: PAGO NÓMINA DEL 09/8/2025 | E76: =SUM(E71:E75) -> 230927
A78: 45879 | B78: Karen Vaquero | D78: 12 a 7 30 | E78: 90216 | L78: 7.5
B79: Yomara González | D79: 1 a 8 30 | E79: 90202 | F79: 7.5
B80: Natalia Ríos | D80: 3 a 8 30 | E80: 67936 | J80: 5.5
A84: PAGO NÓMINA DEL 10/8/2025 | E84: =SUM(E78:E83) -> 248354
A86: 45880 | B86: Karen Vaquero | D86: 11 a 7 30 | E86: 61669 | L86: 8.5
B87: Laura Pulecio | D87: 2 30 a 7 | E87: 35785
B88: Yessica Viscaya | D88: 4 a 8 30 | E88: 35785 | K88: 4.5
B89: Natalia Ríos | D89: 9 a 4 | E89: 51963 | J89: 7
A93: PAGO NÓMINA DEL 11/8/2025 | E93: =SUM(E86:E92) -> 185202
A95: 45881 | B95: Karen Vaquero | D95: 2 a 8 30 | E95: 48727 | L95: 6.5
B96: Laura Pulecio | D96: 2 30 a 7 | E96: 35785
B97: Yomara Gonzalez | D97: 11 a 8 30 | E97: 68140 | F97: 9.5
B98: Natalia Ríos | D98: 9 a 4 | E98: 51963 | J98: 7
B99: Olga Pulecio | D99: Pago | E99: 61332
A101: PAGO NÓMINA DEL 12/8/2025 | E101: =SUM(E95:E100) -> 265947
A103: 45882 | B103: yessica Viscaya | D103: 4 a 8 30 | E103: 35785 | K103: 4.5
B104: Yomara Gonzalez | D104: 11 a 8 30 | E104: 68140 | F104: 9.5
B105: Natalia Ríos | D105: 9 a 4 | E105: 51963 | J105: 7
B106: Olga Pulecio | D106: Pago | E106: 34666
A109: PAGO NÓMINA DEL 13/8/2025 | E109: =SUM(E103:E108) -> 190554
A111: 45883 | B111: Karen Vaquero | D111: 2 a 8 30 | E111: 48727 | L111: 6.5
B112: Laura Pulecio | D112: 3 a 7 30 | E112: 35785
B113: Yomara Gonzalez | D113: 10 30 a 8 30 | E113: 71376 | F113: 10
B114: Natalia Ríos
A118: PAGO NÓMINA DEL 14/8/2025 | E118: =SUM(E111:E117) -> 155888
A120: 45884 | B120: Karen Vaquero | D120: 11 a 7 | E120: 58434 | L120: 8
B121: Yessica Viscaya | D121: 4 a 9 | E121: 39021 | K121: 5
B122: Yomara Gonzalez | D122: 2 a 9 | E122: 51963 | F122: 7
B123: Natalia Ríos | D123: 9 a 4 30 | E123: 55198 | J123: 7.5
A126: PAGO NÓMINA DEL 15/8/2025 | E126: =SUM(E120:E125) -> 204616
A128: 45885 | B128: Karen Vaquero | D128: 1 a 9 30 | E128: 61669 | L128: 8.5
B129: Yomara Gonzalez | D129: 10 a 8 30 | E129: 74611 | F129: 10
B130: Natalia Ríos | D130: 2 a 9 30 | E130: 55192 | J130: 7.5
A132: PAGO NÓMINA DEL 16/8/2025 | E132: =SUM(E128:E131) -> 191472
A134: 45886 | B134: Karen Vaquero | D134: 2 a 8 30 | E134: 79076 | L134: 6.5
B135: Yomara Gonzalez | D135: 11 a 8 | E135: 106926 | F135: 9
B136: Natalia Ríos | D136: 10 a 5 | E136: 84646 | J136: 7
A141: PAGO NÓMINA DEL 17/8/2025 | E141: =SUM(E134:E140) -> 270648
A143: 45887 | B143: Karen Vaquero | D143: 11 a 8 30 | E143: 112496 | L143: 9.5
B144: Yomara Gonzalez | D144: 2 a 830 | E144: 79076 | F144: 6.5
B145: Natalia Ríos | D145: 10 a 5 | E145: 84646 | J145: 7
B146: Santiago Delgado | D146: 2 a 7 30 | E146: 67936
B147: Olga Pulecio | D147: Pago | E147: 57332
A150: PAGO NÓMINA DEL 18/8/2025 | E150: =SUM(E143:E149) -> 401486
A152: 45888 | B152: Karen Vaquero | D152: 11 a 8 | E152: 64905 | L152: 9
B153: Olga Pulecio | D153: Pago | E153: 38666
B154: Natalia Ríos | D154: 9 a 4 | E154: 51963 | J154: 7
B155: Laura Pulecio | D155: 2 30 a 7 | E155: 35785
A157: PAGO NÓMINA DEL 19/8/2025 | E157: =SUM(E152:E156) -> 191319
A159: 20/8"025 | B159: Karen Vaquero
B160: Olga Pulecio | D160: Pago | E160: 34666
B161: Natalia Ríos | D161: 9 a 4 | E161: 51963 | J161: 7
B162: Yomara González | D162: 11 a 7 30 | E162: 61669 | F162: 8.5
...

Sheet Compras
A1: FECHA | B1: NOMBRE | C1: NIT O CC | D1: CONCEPTO | E1: CANTIDAD | F1: VALOR | G1: IVA | H1: TOTAL
A3: 45870 | B3: Éxito | D3: Azúcar | H3: 9950
B4: Natalia | D4: Dedillos | H4: 60000
B5: Fay | D5: 51 5798000 | H5: 98000
B6: Totoa | D6: Panadería | H6: 49000
B7: Rapiplástricos | D7: Desechables | H7: 66200
B8: Éxito | D8: Cervezas frutas | H8: 270200
B9: dólar City | D9: Sodas | H9: 41500
B10: Coordinadora de hielo | D10: Hielo | H10: 13800
B11: Postobón | D11: Tres cordilleras | H11: 47999
B12: Dislicores | D12: Whisky corona | H12: 229687
B13: Frugy | D13: pulpas | H13: 108121
B14: Postobón | D14: Hit | H14: 33400
B15: femsa | D15: Agua | H15: 86400
A22: TOTAL COMPRAS 01/8/2025 | H22: =SUM(H3:H21) -> 1114257
A24: 45871 | B24: Mariela Hurtado | D24: Varios | H24: 95900
B25: Ara | D25: Brownies | H25: 21960
B26: Éxito | D26: Milo leche | H26: 74350
B27: Totoa | D27: Panadería | H27: 58800
B28: Magia | D28: Recibos de caja | H28: 7600
B29: Dólar City | D29: Sodas | H29: 36000
B30: Panamericana | D30: Rollos lápiz | H30: 22100
B31: Fay | D31: 51 56 42 71 | H31: 196000
B32: Coordinadora de hielo | D32: Hielo | H32: 13800
A36: TOTAL COMPRAS 02/8/2025 | H36: =SUM(H24:H35) -> 526510
A38: 45872 | B38: Mercaldas | D38: Frutas | H38: 33500
B39: El perrero | D39: salsa de chocolate | H39: 12900
B40: Éxito | D40: Leche milo servilletas | H40: 137656
B41: Éxito | D41: Zumo | H41: 5180
B42: Cafam | D42: Medicamentos | H42: 8800
B43: Totoa | D43: Panadería | H43: 73000
B44: Alejandro | D44: 59 56 | H44: 100000
A50: TOTAL COMPRAS 03/8/2025 | H50: =SUM(H38:H49) -> 371036
A52: 45873 | B52: Cardonali | D52: 5 tartas | H52: 250000
B53: Gloria Pulecio | D53: 50 frutos secos | H53: 115000
B54: Dólar City | D54: Notas | H54: 15000
B55: Totoa | D55: Panadería | H55: 73000
B56: Éxito | D56: leche chocolate bati crema | H56: 101190
B57: Coordinadora de hielo | D57: Hielo | H57: 13800
B58: Élite | D58: Abono a fra | H58: 100000
B59: ara | D59: Brownies | H59: 31720
B60: Fundadores | D60: Fotocopiaw | H60: 7800
B61: Éxito | D61: Varios | H61: 81824
A64: TOTAL COMPRAS 04/8/2025 | H64: =SUM(H52:H63) -> 789334
A66: 45874 | B66: TOTOA | D66: Panadería | H66: 27600
B67: Dólar City | D67: Desechables | H67: 30000
B68: Ticchi | D68: 10 libras de cafeeé | H68: 270000
B69: Disney + | D69: Suscripcion | H69: 24900
B70: Fay | D70: 4 taras | H70: 196000
A75: TOTAL COMPRAS 05/8/2025 | H75: =SUM(H66:H74) -> 548500
A77: 45875 | B77: Pasteur | D77: Medicamentos | H77: 8408
B78: Rapiplásticos | D78: Desecchables | H78: 65150
B79: Dólar City | D79: Azúcar | H79: 12000
B80: Éxito | D80: Azúcar esencias | H80: 78310
B81: Dólar City | D81: Soda alcohol | H81: 60000
B82: Coordinadora de hielo | D82: Hielo | H82: 13800
B83: Meals de colombia | D83: Helado | H83: 424039
A90: TOTAL COMPRAS 06/8/2025 | H90: =SUM(H77:H89) -> 661707
A92: 45876 | B92: Dólar City | D92: Sodas | H92: 60000
B93: Fabiola Serna | D93: 4 tartas | H93: 184000
B94: Fruver | D94: Frutas | H94: 45750
B95: Éxito | D95: Leche zzúcar bati crema | H95: 149270
B96: Fay | D96: 57 59 51 | H96: 146000
B97: Picasso | D97: Rollos termicos | H97: 19200
B98: Totoa | D98: panadería51600 | H98: 51600
B99: Mariela hurtado | D99: Varios | H99: 119500
A103: TOTAL COMPRAS 07/8/2025 | H103: =SUM(H92:H102) -> 775320
A105: 45877 | B105: Fay | D105: 51 71 42 | H105: 146000
B106: Éxito | D106: Leche zumo y servilletas | H106: 127140
B107: Totoa | D107: Panadería | H107: 73500
B108: Coordinadora de hielo | D108: Hielo | H108: 13800
B109: Frugy | D109: Pulpas | H109: 160543
B110: dislicores | D110: Corona y baileys | H110: 183071
B111: Femsa | D111: agua | H111: 115200
A115: TOTAL COMPRAS 08/8/2025 | H115: =SUM(H105:H114) -> 819254
A117: 45878 | B117: Ara | D117: Brownies | H117: 39590
B118: Éxito | D118: cervezas | H118: 63000
B119: Totoa | D119: Panadería | H119: 75000
B120: Éxito | D120: Ron | H120: 27965
B121: Coordinadora de hielo | D121: Hielo | H121: 13800
B122: Fay | D122: 71 42 56 51 | H122: 196000
B123: Postobón | D123: Tamarindo | H123: 51799
B124: Éxito | D124: Zumos y bati crema | H124: 55200
A130: TOTAL COMPRAS 09/8/2025 | H130: =SUM(H117:H129) -> 522354
A132: 45879 | B132: Dólar City | D132: cuchara helado | H132: 14500
B133: Dólar City | D133: Sodas | H133: 24000
B134: Éxito | D134: Manzanas | H134: 15100
B135: Cardonali | D135: Tarats | H135: 100000
B136: Éxito | D136: Leche desechables servilletas | H136: 143800
B137: Dólar City | D137: Desechables sodas | H137: 83500
B138: Dólar City | D138: Paltos | H138: 28000
B139: Mariela hurtado | D139: Varios | H139: 80100
A143: TOTAL COMPRAS 10/8/2025 | H143: =SUM(H132:H142) -> 489000
A145: 45880 | B145: Rapiplásticos | D145: Desechablwes | H145: 66600
B146: Éxito | D146: leche servilletas | H146: 130370
B147: Pasteur | D147: medicamentos Gloria | H147: 33008
B148: Fay | D148: 71 66 56 51 | H148: 196000
B149: Coordinadora de hielo | D149: Hielo | H149: 13800
B150: Ticchi | D150: 10 libras d ecafé | H150: 270000
A153: TOTAL COMPRAS 11/8/2025 | H153: =SUM(H145:H152) -> 709778
...

Sheet Servicios
A1: FECHA | B1: NOMBRE | C1: NIT | D1: VALOR
A3: 1978/2025 | B3: Aguas de manizales | E3: 146650
B4: Direct tv | E4: 135000
D8: =SUM(D3:D7) -> 0

Sheet Otros Pagos
A1: FECHA | B1: NOMBRE | C1: NIT O CC | D1: CONCEPTO | E1: VALOR | F1: IVA | G1: TOTAL
A3: 45879 | B3: Juan Carlos Londoño | D3: Bonificación | G3: 150000
A6: OTROS PAGOS 10/8/2025 | G6: =SUM(G3:G5) -> 150000
A8: 45889 | B8: César Pulecio | D8: Pago almuerzos fuesta de Ismael | G8: 307900
A11: OTROS PAGOS 20/8/2025 | G11: =SUM(G8:G10) -> 307900
A13: 45896 | B13: Juan | D13: Bonificación | G13: 150000
A15: OTROS PAGOS 27/8/2025 | G15: =SUM(G13:G14) -> 150000
G148: =SUM(G5:G147)/2 -> 532900

Sheet CUENTA POR PAGAR
A2: CUENTAS POR PAGAR
A4: PROVEEDOR | B4: VALOR
A6: DAVID MEJIA
A7: TICCHI CAFFE
A8: ARIAS Y CIA
A9: ARIAS Y CIA
A10: ARIAS Y CIA
A11: ARIAS Y CIA
A12: Juan de Hoyos
A13: Juan de Hoyos
B18: =SUM(B6:B17) -> 0

Sheet Sueldos_ENERO
C2: MARZO
B4: GERALDINE LONDOÑO | H4: MARIANA DELGADO | N4: YISEL LONDOÑO | T4: GERALDINE LONDOÑO | Z4: PAULA MARCELA RUA | AF4: VANESSA CRUZ | AL4: DANIELA GÓMEZ
A38: TOTAL | E38: =SUM(E6:E37) -> 0 | K38: =SUM(K6:K37) -> 0 | Q38: =SUM(Q6:Q35) -> 0 | W38: =SUM(W6:W37) -> 0 | AC38: =SUM(AC6:AC37) -> 0 | AI38: =SUM(AI6:AI37) -> 0 | AO38: =SUM(AO6:AO37) -> 0
